functions_by_cloudproject/README.md
functions_by_cloudproject/math.py
functions_by_cloudproject-0.3.0.dist-info/WHEEL
functions_by_cloudproject-0.3.0.dist-info/METADATA
functions_by_cloudproject-0.3.0.dist-info/RECORD
